mindfold/__init__.py
mindfold/__main__.py
mindfold/example.py
mindfold-0.0.1.dist-info/entry_points.txt
mindfold-0.0.1.dist-info/LICENSE
mindfold-0.0.1.dist-info/METADATA
mindfold-0.0.1.dist-info/WHEEL
mindfold-0.0.1.dist-info/RECORD
